django_browserid/__init__.py
django_browserid/admin.py
django_browserid/auth.py
django_browserid/base.py
django_browserid/compat.py
django_browserid/helpers.py
django_browserid/http.py
django_browserid/signals.py
django_browserid/urls.py
django_browserid/util.py
django_browserid/views.py
django_browserid/static/browserid/api.js
django_browserid/static/browserid/autologin.js
django_browserid/static/browserid/browserid.js
django_browserid/static/browserid/jquery-1.10.2.min.js
django_browserid/static/browserid/persona-buttons.css
django_browserid/templates/browserid/admin_login.html
django_browserid/templates/browserid/button.html
django_browserid/templates/browserid/info.html
django_browserid/templatetags/__init__.py
django_browserid/templatetags/browserid.py
django_browserid/tests/__init__.py
django_browserid/tests/models.py
django_browserid/tests/settings.py
django_browserid/tests/test_admin.py
django_browserid/tests/test_auth.py
django_browserid/tests/test_base.py
django_browserid/tests/test_helpers.py
django_browserid/tests/test_http.py
django_browserid/tests/test_urls.py
django_browserid/tests/test_util.py
django_browserid/tests/test_views.py
django_browserid/tests/urls.py
django_browserid-2.0.2.dist-info/DESCRIPTION.rst
django_browserid-2.0.2.dist-info/METADATA
django_browserid-2.0.2.dist-info/RECORD
django_browserid-2.0.2.dist-info/WHEEL
django_browserid-2.0.2.dist-info/metadata.json
django_browserid-2.0.2.dist-info/top_level.txt
docs/Makefile
docs/__init__.py
docs/conf.py
docs/index.rst
docs/make.bat
docs/settings.py
docs/api/javascript.rst
docs/api/python.rst
docs/contributor/authors.rst
docs/contributor/changelog.rst
docs/contributor/guidelines.rst
docs/contributor/setup.rst
docs/user/customization.rst
docs/user/deploying.rst
docs/user/extras.rst
docs/user/intro.rst
docs/user/quickstart.rst
docs/user/settings.rst
docs/user/troubleshooting.rst
docs/user/upgrading.rst
