Metadata-Version: 2.0
Name: django-browserid
Version: 2.0.2
Summary: Django application for adding BrowserID support.
Home-page: https://github.com/mozilla/django-browserid
Author: Paul Osman, Michael Kelly
Author-email: mkelly@mozilla.com
License: MPL v2.0
Platform: UNKNOWN
Classifier: Development Status :: 4 - Beta
Classifier: Environment :: Web Environment
Classifier: Framework :: Django
Classifier: Intended Audience :: Developers
Classifier: License :: OSI Approved :: Mozilla Public License 2.0 (MPL 2.0)
Classifier: Operating System :: OS Independent
Classifier: Programming Language :: Python
Classifier: Programming Language :: Python :: 2.6
Classifier: Programming Language :: Python :: 2.7
Classifier: Programming Language :: Python :: 3.2
Classifier: Programming Language :: Python :: 3.3
Classifier: Programming Language :: Python :: 3.4
Requires-Dist: requests (>=1.0.0)
